.readthedocs.yaml
CONTRIBUTING.md
LICENSE
MANIFEST.in
README.md
SConstruct
gsl-config.bat
pyproject.toml
setup.py
docs/Makefile
docs/capi.rst
docs/conf.py
docs/examples.rst
docs/index.rst
docs/installation.rst
docs/pythonapi.rst
example/Makefile
example/example.c
example/example_flat.c
example/example_split.c
src/.gitignore
src/cquad_const.c
src/err.c
src/lintegrate.h
src/lintegrate_cquad.c
src/lintegrate_qag.c
src/lintegrate_qng.c
src/lintegrate_split.c
src/logadd.c
src/logsub.c
src/qkrules.c
src/qng.h
src/lintegrate/__init__.py
src/lintegrate/_version.py
src/lintegrate/lintegrate.pyx
src/lintegrate.egg-info/PKG-INFO
src/lintegrate.egg-info/SOURCES.txt
src/lintegrate.egg-info/dependency_links.txt
src/lintegrate.egg-info/requires.txt
src/lintegrate.egg-info/top_level.txt
test/test_lintegrate.py