Metadata-Version: 2.1
Name: lintegrate
Version: 0.2.0
Summary: Python functions implementing numerical integration of functions in log-space.
Author-email: Matthew Pitkin <m@ttpitk.in>
License: GPLv3
Project-URL: Homepage, https://github.com/mattpitkin/lintegrate
Project-URL: Documentation, https://lintegrate.readthedocs.io/
Classifier: Intended Audience :: Science/Research
Classifier: License :: OSI Approved :: GNU General Public License v3 or later (GPLv3+)
Classifier: Natural Language :: English
Classifier: Operating System :: POSIX :: Linux
Classifier: Programming Language :: C
Classifier: Programming Language :: Python
Classifier: Programming Language :: Python :: 3.9
Classifier: Programming Language :: Python :: 3.10
Classifier: Programming Language :: Python :: 3.11
Requires-Python: <4,>=3.9
License-File: LICENSE
Requires-Dist: numpy
Provides-Extra: docs
Requires-Dist: autodoc; extra == "docs"
Requires-Dist: pydata-sphinx-theme; extra == "docs"
Requires-Dist: sphinx>=2.0; extra == "docs"
Requires-Dist: sphinx-panels; extra == "docs"
Requires-Dist: sphinxcontrib-napoleon; extra == "docs"
Requires-Dist: sphinxext-remoteliteralinclude; extra == "docs"
